Metadata-Version: 1.1
Name: resourcify
Version: 0.2.6
Summary: Resource library to make ReST client easy
Home-page: http://github.com/Xeite/resourcify
Author: Yang Youseok
Author-email: ileixe@gmail.com
License: MIT License
Keywords: http rest client
Platform: Linux
Classifier: Development Status :: 3 - Alpha
Classifier: Programming Language :: Python :: 3
Classifier: License :: OSI Approved :: MIT License
